topsis_aadi_102303612/__init__.py
topsis_aadi_102303612/topsis.py
topsis_aadi_102303612-1.0.1.dist-info/METADATA
topsis_aadi_102303612-1.0.1.dist-info/WHEEL
topsis_aadi_102303612-1.0.1.dist-info/entry_points.txt
topsis_aadi_102303612-1.0.1.dist-info/top_level.txt
topsis_aadi_102303612-1.0.1.dist-info/RECORD
