Metadata-Version: 2.4
Name: topsis-aadi-102303612
Version: 1.0.1
Summary: TOPSIS implementation
Author: Aadi
Requires-Dist: numpy
Requires-Dist: pandas
Dynamic: author
Dynamic: description
Dynamic: description-content-type
Dynamic: requires-dist
Dynamic: summary
